trigo/__init__.py
trigo-0.3.dist-info/License.txt
trigo-0.3.dist-info/METADATA
trigo-0.3.dist-info/WHEEL
trigo-0.3.dist-info/top_level.txt
trigo-0.3.dist-info/RECORD
